odoo/addons/account_payment_return_import_iso20022/README.rst
odoo/addons/account_payment_return_import_iso20022/__init__.py
odoo/addons/account_payment_return_import_iso20022/__manifest__.py
odoo/addons/account_payment_return_import_iso20022/data/payment.return.reason.csv
odoo/addons/account_payment_return_import_iso20022/i18n/account_payment_return_import_iso20022.pot
odoo/addons/account_payment_return_import_iso20022/i18n/es.po
odoo/addons/account_payment_return_import_iso20022/i18n/it.po
odoo/addons/account_payment_return_import_iso20022/models/__init__.py
odoo/addons/account_payment_return_import_iso20022/models/payment_return.py
odoo/addons/account_payment_return_import_iso20022/readme/CONTRIBUTORS.md
odoo/addons/account_payment_return_import_iso20022/readme/DESCRIPTION.md
odoo/addons/account_payment_return_import_iso20022/readme/INSTALL.md
odoo/addons/account_payment_return_import_iso20022/static/description/icon.png
odoo/addons/account_payment_return_import_iso20022/static/description/index.html
odoo/addons/account_payment_return_import_iso20022/tests/__init__.py
odoo/addons/account_payment_return_import_iso20022/tests/test_import_iso20022.py
odoo/addons/account_payment_return_import_iso20022/tests/test_files/test-sepa-camt-053-unpaid.xml
odoo/addons/account_payment_return_import_iso20022/tests/test_files/test-sepa-camt-054-unpaid.xml
odoo/addons/account_payment_return_import_iso20022/tests/test_files/test-sepa-camt-unpaid-invalid.xml
odoo/addons/account_payment_return_import_iso20022/tests/test_files/test-sepa-camt-unpaid.zip
odoo/addons/account_payment_return_import_iso20022/tests/test_files/test-sepa-pain-unpaid-invalid.xml
odoo/addons/account_payment_return_import_iso20022/tests/test_files/test-sepa-pain-unpaid.xml
odoo/addons/account_payment_return_import_iso20022/tests/test_files/test-sepa-pain-unpaid.zip
odoo/addons/account_payment_return_import_iso20022/wizard/__init__.py
odoo/addons/account_payment_return_import_iso20022/wizard/camt_parser.py
odoo_addon_account_payment_return_import_iso20022-18.0.1.1.0.dist-info/METADATA
odoo_addon_account_payment_return_import_iso20022-18.0.1.1.0.dist-info/WHEEL
odoo_addon_account_payment_return_import_iso20022-18.0.1.1.0.dist-info/top_level.txt
odoo_addon_account_payment_return_import_iso20022-18.0.1.1.0.dist-info/RECORD
