Metadata-Version: 2.1
Name: odoo-addon-account_payment_return_import_iso20022
Version: 18.0.1.1.0
Requires-Python: >=3.10
Requires-Dist: odoo-addon-account_payment_order==18.0.*
Requires-Dist: odoo-addon-account_payment_return_import==18.0.*
Requires-Dist: odoo==18.0.*
Summary: This addon allows to import payment returns from ISO 20022 files like PAIN or CAMT.
Home-page: https://github.com/OCA/account-payment
License: AGPL-3
Author: Odoo Community Association (OCA),Tecnativa,ACSONE SA/NV
Author-email: support@odoo-community.org
Classifier: Programming Language :: Python
Classifier: Framework :: Odoo
Classifier: Framework :: Odoo :: 18.0
Classifier: License :: OSI Approved :: GNU Affero General Public License v3
Classifier: Development Status :: 6 - Mature
